mortgage_copilot/__init__.py
mortgage_copilot/agent/Copilot.py
mortgage_copilot/agent/__init__.py
mortgage_copilot/rag/rag_system.py
mortgage_copilot/utils/extractor.py
mortgage_copilot/utils/model.py
mortgage_copilot-0.1.1.dist-info/METADATA
mortgage_copilot-0.1.1.dist-info/WHEEL
mortgage_copilot-0.1.1.dist-info/top_level.txt
mortgage_copilot-0.1.1.dist-info/RECORD
