Metadata-Version: 2.4
Name: mortgage-copilot
Version: 0.1.1
Summary: Agentic Mortgage Co-Pilot: A reusable, production-ready Python package that plugs generative-AI agents into any mortgage-origination stack.
Author-email: 54g0 <sagar8296d@gmail.com>
Project-URL: Homepage, https://github.com/54g0/Mortgage-Copilot
Classifier: Programming Language :: Python :: 3
Classifier: License :: OSI Approved :: MIT License
Classifier: Operating System :: OS Independent
Requires-Python: >=3.8
Requires-Dist: langchain
Requires-Dist: faiss-cpu
Requires-Dist: pydantic
Requires-Dist: python-multipart
Requires-Dist: openai
Requires-Dist: transformers
Requires-Dist: sentence-transformers
Requires-Dist: accelerate
Requires-Dist: langchain_groq
Requires-Dist: langchain_openai
Requires-Dist: langchain_huggingface
Requires-Dist: huggingface_hub
Requires-Dist: langchain-google-genai
Requires-Dist: langchain-community
Requires-Dist: easyocr
Requires-Dist: camelot-py
Requires-Dist: PyPDF2
Requires-Dist: pdfplumber
Requires-Dist: pandas
Requires-Dist: numpy
Requires-Dist: tabulate
Requires-Dist: langgraph
